LICENSE
README.md
setup.py
casino_dice/__init__.py
casino_dice/casino_dice.py
casino_dice.egg-info/PKG-INFO
casino_dice.egg-info/SOURCES.txt
casino_dice.egg-info/dependency_links.txt
casino_dice.egg-info/top_level.txt
tests/__init__.py
tests/unit_tests.py