Metadata-Version: 2.1
Name: casino-dice
Version: 1.0.1
Summary: A library for generating byte objects from physical casino dice rolls
Home-page: https://github.com/anthony-ozdemir/casino-dice
Author: Anthony V. Ozdemir
Author-email: anthony@anthonyozdemir.com
Classifier: Development Status :: 5 - Production/Stable
Classifier: Intended Audience :: Developers
Classifier: Intended Audience :: Other Audience
Classifier: License :: OSI Approved :: MIT License
Classifier: Operating System :: OS Independent
Classifier: Programming Language :: Python :: 3
Classifier: Programming Language :: Python :: 3.7
Classifier: Programming Language :: Python :: 3.8
Classifier: Programming Language :: Python :: 3.9
Classifier: Topic :: Security
Classifier: Topic :: Security :: Cryptography
Requires-Python: >=3.7
License-File: LICENSE
